LICENSE
pyproject.toml
.github/README.md
src_agent/__init__.py
src_agent/entrypoint.py
src_agent-0.0.1.dist-info/METADATA
src_agent-0.0.1.dist-info/WHEEL
src_agent-0.0.1.dist-info/entry_points.txt
src_agent-0.0.1.dist-info/licenses/LICENSE
src_agent-0.0.1.dist-info/RECORD
