Metadata-Version: 2.4
Name: src-agent
Version: 0.0.1
Summary: Simple coding agent.
License-Expression: MIT
License-File: LICENSE
Requires-Python: >=3.10
Requires-Dist: openai
Requires-Dist: pyyaml
Provides-Extra: developer
Requires-Dist: bandit; extra == 'developer'
Requires-Dist: black; extra == 'developer'
Requires-Dist: hatch; extra == 'developer'
Requires-Dist: jinja2; extra == 'developer'
Requires-Dist: mypy; extra == 'developer'
Requires-Dist: pytest; extra == 'developer'
Requires-Dist: ruff; extra == 'developer'
